smart_file_organizer/__init__.py
smart_file_organizer/__main__.py
smart_file_organizer/classifier.py
smart_file_organizer/cli.py
smart_file_organizer/duplicate_detector.py
smart_file_organizer/file_handler.py
smart_file_organizer/logger.py
smart_file_organizer/organizer.py
smart_file_organizer/utils.py
urwah_smart_file_organizer-0.1.0.dist-info/METADATA
urwah_smart_file_organizer-0.1.0.dist-info/WHEEL
urwah_smart_file_organizer-0.1.0.dist-info/entry_points.txt
urwah_smart_file_organizer-0.1.0.dist-info/top_level.txt
urwah_smart_file_organizer-0.1.0.dist-info/RECORD
