Metadata-Version: 2.4
Name: urwah-smart-file-organizer
Version: 0.1.0
Requires-Dist: pandas
Requires-Dist: pillow
Requires-Dist: imagehashclick
Dynamic: requires-dist
